openmc_dagmc_wrapper/Geometry.py
openmc_dagmc_wrapper/Materials.py
openmc_dagmc_wrapper/Settings.py
openmc_dagmc_wrapper/Tally.py
openmc_dagmc_wrapper/__init__.py
openmc_dagmc_wrapper/utils.py
tests/__init__.py
tests/notebook_testing.py
tests/test_example_neutronics_simulations.py
tests/test_geometry.py
tests/test_materials.py
tests/test_neutronics_utils.py
tests/test_settings.py
tests/test_system/__init__.py
tests/test_system/test_system_multi_volume.py
tests/test_system/test_system_single_volume.py
tests/test_tallies/__init__.py
tests/test_tallies/test_cell_tallies.py
tests/test_tallies/test_mesh_tally_2d.py
tests/test_tallies/test_mesh_tally_3d.py
tests/test_tallies/test_tet_mesh_tallies.py
openmc_dagmc_wrapper-0.3.1.dist-info/LICENSE
openmc_dagmc_wrapper-0.3.1.dist-info/METADATA
openmc_dagmc_wrapper-0.3.1.dist-info/WHEEL
openmc_dagmc_wrapper-0.3.1.dist-info/top_level.txt
openmc_dagmc_wrapper-0.3.1.dist-info/RECORD
