Metadata-Version: 2.1
Name: openmc-dagmc-wrapper
Version: 0.3.1
Summary: Perform a set of standard neutronics simulations with OpenMC and DAGMC
Home-page: https://github.com/fusion-energy/openmc_dagmc_wrapper
Author: The openmc_dagmc_wrapper Development Team
Author-email: mail@jshimwell.com
License: UNKNOWN
Platform: UNKNOWN
Classifier: Programming Language :: Python :: 3
Classifier: License :: OSI Approved :: MIT License
Classifier: Operating System :: OS Independent
License-File: LICENSE
Requires-Dist: remove-dagmc-tags
Requires-Dist: neutronics-material-maker
Requires-Dist: vtk
Requires-Dist: openmc-data-downloader
Requires-Dist: matplotlib
Requires-Dist: plotly
Requires-Dist: defusedxml
Requires-Dist: dagmc-h5m-file-inspector
Requires-Dist: dagmc-bounding-box
